fldpln/__init__.py
fldpln/common.py
fldpln/gauge.py
fldpln/mapping.py
fldpln/model.py
fldpln/tile.py
fldpln-0.0.15.dist-info/licenses/LICENSE
fldpln_py/fldpln_py_Installer_web.exe
fldpln-0.0.15.dist-info/METADATA
fldpln-0.0.15.dist-info/WHEEL
fldpln-0.0.15.dist-info/entry_points.txt
fldpln-0.0.15.dist-info/top_level.txt
fldpln-0.0.15.dist-info/RECORD
