Metadata-Version: 2.4
Name: fldpln
Version: 0.0.15
Summary: Flood inundation modeling and mapping using the FLDPLN model
Author-email: Xingong Li <lixi@ku.edu>
License: MIT License
Project-URL: Homepage, https://github.com/xingongli/fldpln
Keywords: fldpln
Classifier: Intended Audience :: Developers
Classifier: License :: OSI Approved :: MIT License
Classifier: Natural Language :: English
Classifier: Programming Language :: Python :: 3.8
Classifier: Programming Language :: Python :: 3.9
Classifier: Programming Language :: Python :: 3.10
Classifier: Programming Language :: Python :: 3.11
Classifier: Programming Language :: Python :: 3.12
Requires-Python: >=3.8
License-File: LICENSE
Requires-Dist: numpy
Requires-Dist: pandas
Requires-Dist: geopandas
Requires-Dist: scipy
Requires-Dist: h5py
Requires-Dist: shapely
Requires-Dist: rasterio
Requires-Dist: rio_cogeo
Requires-Dist: pyproj
Requires-Dist: lxml
Provides-Extra: all
Requires-Dist: fldpln[extra]; extra == "all"
Provides-Extra: extra
Requires-Dist: pandas; extra == "extra"
Dynamic: license-file
